[
  {
    "url": "https://github.com/wangkuiyi",
    "language": "Racket",
    "full_name": "",
    "username": "wangkuiyi",
    "location": "",
    "join_date": "Mar 17, 2012",
    "popular_repos_stars": "122",
    "primary_languages": [
      "Go",
      "Shell",
      "C"
    ],
    "contributions": 48,
    "followers": "315"
  },
  {
    "url": "https://github.com/tonyg",
    "language": "Racket",
    "full_name": "Tony Garnock-Jones",
    "username": "tonyg",
    "location": "Cambridge, MA",
    "join_date": "Jul 21, 2008",
    "popular_repos_stars": "805",
    "primary_languages": [
      "Racket",
      "C",
      "Python"
    ],
    "contributions": 1,
    "followers": "193"
  },
  {
    "url": "https://github.com/lkuper",
    "language": "Racket",
    "full_name": "Lindsey Kuper",
    "username": "lkuper",
    "location": "",
    "join_date": "Dec 23, 2010",
    "popular_repos_stars": "55",
    "primary_languages": [
      "JavaScript",
      "Shell",
      "Haskell"
    ],
    "contributions": 1,
    "followers": "109"
  },
  {
    "url": "https://github.com/plt",
    "language": "Racket",
    "full_name": "PLT",
    "username": "plt",
    "location": "",
    "join_date": "Jan 19, 2010",
    "popular_repos_stars": "733",
    "primary_languages": [
      "Racket",
      "Scheme",
      "Python"
    ],
    "contributions": 0,
    "followers": "109"
  },
  {
    "url": "https://github.com/mflatt",
    "language": "Racket",
    "full_name": "Matthew Flatt",
    "username": "mflatt",
    "location": "",
    "join_date": "Jun 2, 2010",
    "popular_repos_stars": "58",
    "primary_languages": [
      "Racket",
      "Shell",
      "JavaScript"
    ],
    "contributions": 1,
    "followers": "103"
  },
  {
    "url": "https://github.com/samth",
    "language": "Racket",
    "full_name": "Sam Tobin-Hochstadt",
    "username": "samth",
    "location": "Bloomington, IN",
    "join_date": "Apr 15, 2010",
    "popular_repos_stars": "85",
    "primary_languages": [
      "Racket",
      "Shell",
      "JavaScript"
    ],
    "contributions": 1,
    "followers": "100"
  },
  {
    "url": "https://github.com/jeapostrophe",
    "language": "Racket",
    "full_name": "Jay McCarthy",
    "username": "jeapostrophe",
    "location": "Poughkeepsie, NY",
    "join_date": "Mar 29, 2010",
    "popular_repos_stars": "59",
    "primary_languages": [
      "Racket",
      "Scheme",
      "JavaScript"
    ],
    "contributions": 1,
    "followers": "94"
  },
  {
    "url": "https://github.com/dvanhorn",
    "language": "Racket",
    "full_name": "David Van Horn",
    "username": "dvanhorn",
    "location": "Washington, DC",
    "join_date": "Feb 17, 2010",
    "popular_repos_stars": "44",
    "primary_languages": [
      "Racket",
      "Scheme",
      "Shell"
    ],
    "contributions": 332,
    "followers": "83"
  },
  {
    "url": "https://github.com/dyoo",
    "language": "Racket",
    "full_name": "Danny Yoo",
    "username": "dyoo",
    "location": "Mountain View, CA",
    "join_date": "Mar 25, 2009",
    "popular_repos_stars": "244",
    "primary_languages": [
      "Racket",
      "JavaScript",
      "Scheme"
    ],
    "contributions": 4,
    "followers": "73"
  },
  {
    "url": "https://github.com/greghendershott",
    "language": "Racket",
    "full_name": "Greg Hendershott",
    "username": "greghendershott",
    "location": "Boston, USA",
    "join_date": "May 4, 2010",
    "popular_repos_stars": "317",
    "primary_languages": [
      "Racket",
      "Shell",
      "CSS"
    ],
    "contributions": 1,
    "followers": "64"
  },
  {
    "url": "https://github.com/elibarzilay",
    "language": "Racket",
    "full_name": "Eli Barzilay",
    "username": "elibarzilay",
    "location": "",
    "join_date": "Jan 19, 2010",
    "popular_repos_stars": "18",
    "primary_languages": [
      "Racket",
      "Shell",
      "Emacs",
      "Lisp"
    ],
    "contributions": 79,
    "followers": "62"
  },
  {
    "url": "https://github.com/shriram",
    "language": "Racket",
    "full_name": "Shriram Krishnamurthi",
    "username": "shriram",
    "location": "",
    "join_date": "Apr 17, 2009",
    "popular_repos_stars": "63",
    "primary_languages": [
      "Racket",
      "CSS",
      "JavaScript"
    ],
    "contributions": 277,
    "followers": "55"
  },
  {
    "url": "https://github.com/takikawa",
    "language": "Racket",
    "full_name": "Asumu Takikawa",
    "username": "takikawa",
    "location": "Boston, MA",
    "join_date": "Mar 17, 2009",
    "popular_repos_stars": "129",
    "primary_languages": [
      "Racket",
      "Shell",
      "C"
    ],
    "contributions": 736,
    "followers": "54"
  },
  {
    "url": "https://github.com/jbclements",
    "language": "Racket",
    "full_name": "John Clements",
    "username": "jbclements",
    "location": "",
    "join_date": "Mar 19, 2010",
    "popular_repos_stars": "51",
    "primary_languages": [
      "Racket",
      "C",
      "Scheme"
    ],
    "contributions": 426,
    "followers": "45"
  },
  {
    "url": "https://github.com/danking",
    "language": "Racket",
    "full_name": "Daniel King",
    "username": "danking",
    "location": "Boston, MA",
    "join_date": "Jul 17, 2009",
    "popular_repos_stars": "25",
    "primary_languages": [
      "Racket",
      "Shell",
      "Haskell"
    ],
    "contributions": 270,
    "followers": "36"
  },
  {
    "url": "https://github.com/mfelleisen",
    "language": "Racket",
    "full_name": "Matthias Felleisen",
    "username": "mfelleisen",
    "location": "Boston ",
    "join_date": "Mar 24, 2012",
    "popular_repos_stars": "5",
    "primary_languages": [
      "Racket",
      "TeX"
    ],
    "contributions": 81,
    "followers": "36"
  },
  {
    "url": "https://github.com/soegaard",
    "language": "Racket",
    "full_name": "Jens Axel Søgaard",
    "username": "soegaard",
    "location": "",
    "join_date": "Oct 31, 2010",
    "popular_repos_stars": "53",
    "primary_languages": [
      "Racket",
      "JavaScript",
      "Scheme"
    ],
    "contributions": 461,
    "followers": "34"
  },
  {
    "url": "https://github.com/aturon",
    "language": "Racket",
    "full_name": "Aaron Turon",
    "username": "aturon",
    "location": "San Francisco, USA",
    "join_date": "Apr 4, 2011",
    "popular_repos_stars": "33",
    "primary_languages": [
      "JavaScript",
      "Racket",
      "Shell"
    ],
    "contributions": 186,
    "followers": "33"
  },
  {
    "url": "https://github.com/rfindler",
    "language": "Racket",
    "full_name": "Robby Findler",
    "username": "rfindler",
    "location": "",
    "join_date": "Sep 14, 2010",
    "popular_repos_stars": "5",
    "primary_languages": [
      "Racket",
      "JavaScript",
      "Shell"
    ],
    "contributions": 1,
    "followers": "32"
  },
  {
    "url": "https://github.com/serghey-rodin",
    "language": "Racket",
    "full_name": "Serghey Rodin",
    "username": "serghey-rodin",
    "location": "",
    "join_date": "Jun 11, 2011",
    "popular_repos_stars": "260",
    "primary_languages": [
      "Shell",
      "PHP",
      "C"
    ],
    "contributions": 430,
    "followers": "31"
  },
  {
    "url": "https://github.com/stamourv",
    "language": "Racket",
    "full_name": "Vincent St-Amour",
    "username": "stamourv",
    "location": "Boston, MA, USA",
    "join_date": "Jun 16, 2011",
    "popular_repos_stars": "82",
    "primary_languages": [
      "Racket",
      "Shell",
      "Scheme"
    ],
    "contributions": 476,
    "followers": "31"
  },
  {
    "url": "https://github.com/saki7",
    "language": "Racket",
    "full_name": "Nana Sakisaka",
    "username": "saki7",
    "location": "Tokyo, Japan",
    "join_date": "Jun 28, 2012",
    "popular_repos_stars": "2",
    "primary_languages": [
      "Ruby",
      "C",
      "Shell"
    ],
    "contributions": 97,
    "followers": "29"
  },
  {
    "url": "https://github.com/NashaLyaLya",
    "language": "Racket",
    "full_name": "",
    "username": "NashaLyaLya",
    "location": "",
    "join_date": "Aug 1, 2013",
    "popular_repos_stars": "0",
    "primary_languages": [],
    "contributions": 0,
    "followers": "28"
  },
  {
    "url": "https://github.com/stchang",
    "language": "Racket",
    "full_name": "Stephen Chang",
    "username": "stchang",
    "location": "Boston, MA",
    "join_date": "Oct 12, 2008",
    "popular_repos_stars": "52",
    "primary_languages": [
      "Racket",
      "CSS",
      "Shell"
    ],
    "contributions": 419,
    "followers": "27"
  },
  {
    "url": "https://github.com/rmculpepper",
    "language": "Racket",
    "full_name": "Ryan Culpepper",
    "username": "rmculpepper",
    "location": "Boston, MA",
    "join_date": "Mar 21, 2011",
    "popular_repos_stars": "24",
    "primary_languages": [
      "Racket",
      "Shell",
      "Scheme"
    ],
    "contributions": 668,
    "followers": "25"
  },
  {
    "url": "https://github.com/Krolechka",
    "language": "Racket",
    "full_name": "",
    "username": "Krolechka",
    "location": "",
    "join_date": "Aug 1, 2013",
    "popular_repos_stars": "0",
    "primary_languages": [],
    "contributions": 0,
    "followers": "23"
  },
  {
    "url": "https://github.com/arjunblj",
    "language": "Racket",
    "full_name": "Arjun Balaji",
    "username": "arjunblj",
    "location": "Boston, MA",
    "join_date": "May 6, 2012",
    "popular_repos_stars": "12",
    "primary_languages": [
      "Ruby",
      "JavaScript",
      "CSS"
    ],
    "contributions": 83,
    "followers": "23"
  },
  {
    "url": "https://github.com/jpverkamp",
    "language": "Racket",
    "full_name": "JP Verkamp",
    "username": "jpverkamp",
    "location": "Burlingame, CA",
    "join_date": "Jun 30, 2009",
    "popular_repos_stars": "27",
    "primary_languages": [
      "Racket",
      "Python",
      "Shell"
    ],
    "contributions": 563,
    "followers": "22"
  },
  {
    "url": "https://github.com/stoye",
    "language": "Racket",
    "full_name": "Steven Toye",
    "username": "stoye",
    "location": "",
    "join_date": "Feb 25, 2013",
    "popular_repos_stars": "1",
    "primary_languages": [
      "CSS",
      "Python",
      "Shell"
    ],
    "contributions": 140,
    "followers": "21"
  },
  {
    "url": "https://github.com/shekari",
    "language": "Racket",
    "full_name": "Eric Dobson",
    "username": "shekari",
    "location": "Mountain View, CA",
    "join_date": "Dec 19, 2009",
    "popular_repos_stars": "47",
    "primary_languages": [
      "Racket",
      "Shell",
      "JavaScript"
    ],
    "contributions": 630,
    "followers": "21"
  },
  {
    "url": "https://github.com/Elfindora",
    "language": "Racket",
    "full_name": "",
    "username": "Elfindora",
    "location": "",
    "join_date": "Aug 2, 2013",
    "popular_repos_stars": "0",
    "primary_languages": [],
    "contributions": 0,
    "followers": "20"
  },
  {
    "url": "https://github.com/Malati",
    "language": "Racket",
    "full_name": "",
    "username": "Malati",
    "location": "",
    "join_date": "Aug 1, 2013",
    "popular_repos_stars": "0",
    "primary_languages": [],
    "contributions": 0,
    "followers": "20"
  },
  {
    "url": "https://github.com/wija",
    "language": "Racket",
    "full_name": "Bill Abresch",
    "username": "wija",
    "location": "",
    "join_date": "Jan 1, 2013",
    "popular_repos_stars": "8",
    "primary_languages": [
      "JavaScript",
      "Racket",
      "Shell"
    ],
    "contributions": 26,
    "followers": "20"
  },
  {
    "url": "https://github.com/rodrigobaron",
    "language": "Racket",
    "full_name": "Rodrigo Baron",
    "username": "rodrigobaron",
    "location": "Brazil",
    "join_date": "May 16, 2011",
    "popular_repos_stars": "2",
    "primary_languages": [
      "JavaScript",
      "CSS",
      "Shell"
    ],
    "contributions": 139,
    "followers": "20"
  },
  {
    "url": "https://github.com/silverbullettt",
    "language": "Racket",
    "full_name": "TT",
    "username": "silverbullettt",
    "location": "",
    "join_date": "Dec 10, 2011",
    "popular_repos_stars": "6",
    "primary_languages": [
      "Racket",
      "Perl",
      "Scheme"
    ],
    "contributions": 0,
    "followers": "19"
  },
  {
    "url": "https://github.com/florence",
    "language": "Racket",
    "full_name": "Spencer Florence",
    "username": "florence",
    "location": "Boston, MA",
    "join_date": "Feb 6, 2012",
    "popular_repos_stars": "15",
    "primary_languages": [
      "Racket",
      "Shell",
      "CSS"
    ],
    "contributions": 258,
    "followers": "19"
  },
  {
    "url": "https://github.com/basdirks",
    "language": "Racket",
    "full_name": "Bas Dirks",
    "username": "basdirks",
    "location": "The Netherlands",
    "join_date": "Jan 22, 2011",
    "popular_repos_stars": "0",
    "primary_languages": [
      "Swift",
      "Haskell",
      "Shell"
    ],
    "contributions": 21,
    "followers": "19"
  },
  {
    "url": "https://github.com/ntoronto",
    "language": "Racket",
    "full_name": "Neil Toronto",
    "username": "ntoronto",
    "location": "",
    "join_date": "Nov 19, 2010",
    "popular_repos_stars": "27",
    "primary_languages": [
      "Racket",
      "Shell",
      "Haskell"
    ],
    "contributions": 127,
    "followers": "18"
  },
  {
    "url": "https://github.com/mmxtrem",
    "language": "Racket",
    "full_name": "miroslav_mm",
    "username": "mmxtrem",
    "location": "Kiev",
    "join_date": "Apr 10, 2011",
    "popular_repos_stars": "8",
    "primary_languages": [
      "C",
      "Shell",
      "C"
    ],
    "contributions": 0,
    "followers": "17"
  },
  {
    "url": "https://github.com/MissLine",
    "language": "Racket",
    "full_name": "",
    "username": "MissLine",
    "location": "",
    "join_date": "Aug 3, 2013",
    "popular_repos_stars": "0",
    "primary_languages": [],
    "contributions": 0,
    "followers": "17"
  },
  {
    "url": "https://github.com/pablofdezalc",
    "language": "Racket",
    "full_name": "Pablo F. Alcantarilla",
    "username": "pablofdezalc",
    "location": "Cambridge, UK",
    "join_date": "Dec 23, 2011",
    "popular_repos_stars": "76",
    "primary_languages": [
      "C",
      "Shell",
      "C"
    ],
    "contributions": 84,
    "followers": "17"
  },
  {
    "url": "https://github.com/Unsuri",
    "language": "Racket",
    "full_name": "",
    "username": "Unsuri",
    "location": "",
    "join_date": "Aug 1, 2013",
    "popular_repos_stars": "0",
    "primary_languages": [],
    "contributions": 0,
    "followers": "16"
  },
  {
    "url": "https://github.com/josefalcon",
    "language": "Racket",
    "full_name": "Jose Falcon",
    "username": "josefalcon",
    "location": "",
    "join_date": "Jan 25, 2011",
    "popular_repos_stars": "8",
    "primary_languages": [
      "JavaScript",
      "Ruby",
      "Shell"
    ],
    "contributions": 133,
    "followers": "14"
  },
  {
    "url": "https://github.com/carl-eastlund",
    "language": "Racket",
    "full_name": "Carl Eastlund",
    "username": "carl-eastlund",
    "location": "New York, NY",
    "join_date": "Mar 16, 2012",
    "popular_repos_stars": "3",
    "primary_languages": [
      "Racket",
      "Rust",
      "Objective",
      "C"
    ],
    "contributions": 35,
    "followers": "14"
  },
  {
    "url": "https://github.com/jrslepak",
    "language": "Racket",
    "full_name": "Justin Slepak",
    "username": "jrslepak",
    "location": "Boston, MA",
    "join_date": "Apr 19, 2010",
    "popular_repos_stars": "8",
    "primary_languages": [
      "Racket",
      "C",
      "Haskell"
    ],
    "contributions": 100,
    "followers": "14"
  },
  {
    "url": "https://github.com/capnmidnight",
    "language": "Racket",
    "full_name": "Sean T. McBeth",
    "username": "capnmidnight",
    "location": "Alexandria, VA",
    "join_date": "Jun 6, 2010",
    "popular_repos_stars": "17",
    "primary_languages": [
      "C",
      "JavaScript",
      "CSS"
    ],
    "contributions": 814,
    "followers": "14"
  },
  {
    "url": "https://github.com/vanessa007",
    "language": "Racket",
    "full_name": "",
    "username": "vanessa007",
    "location": "",
    "join_date": "Apr 28, 2013",
    "popular_repos_stars": "4",
    "primary_languages": [
      "Java",
      "Racket",
      "Haskell"
    ],
    "contributions": 43,
    "followers": "13"
  },
  {
    "url": "https://github.com/dwayne",
    "language": "Racket",
    "full_name": "Dwayne Crooks",
    "username": "dwayne",
    "location": "Trinidad and Tobago",
    "join_date": "Jun 30, 2010",
    "popular_repos_stars": "15",
    "primary_languages": [
      "Ruby",
      "JavaScript",
      "CSS"
    ],
    "contributions": 480,
    "followers": "13"
  },
  {
    "url": "https://github.com/Linzertorte",
    "language": "Racket",
    "full_name": "Zhaoliang Liu",
    "username": "Linzertorte",
    "location": "",
    "join_date": "Sep 7, 2013",
    "popular_repos_stars": "10",
    "primary_languages": [
      "C",
      "Python",
      "Java"
    ],
    "contributions": 789,
    "followers": "13"
  },
  {
    "url": "https://github.com/gmarceau",
    "language": "Racket",
    "full_name": "Guillaume Marceau",
    "username": "gmarceau",
    "location": "",
    "join_date": "Jun 2, 2011",
    "popular_repos_stars": "8",
    "primary_languages": [
      "Racket",
      "JavaScript",
      "Scheme"
    ],
    "contributions": 18,
    "followers": "11"
  },
  {
    "url": "https://github.com/kaicheng",
    "language": "Racket",
    "full_name": "Kaicheng Zhang",
    "username": "kaicheng",
    "location": "Evanston, IL",
    "join_date": "Oct 10, 2012",
    "popular_repos_stars": "40",
    "primary_languages": [
      "JavaScript",
      "Go",
      "Shell"
    ],
    "contributions": 140,
    "followers": "11"
  },
  {
    "url": "https://github.com/evykassirer",
    "language": "Racket",
    "full_name": "Evy Kassirer",
    "username": "evykassirer",
    "location": "",
    "join_date": "Oct 7, 2013",
    "popular_repos_stars": "5",
    "primary_languages": [
      "C",
      "JavaScript",
      "CSS"
    ],
    "contributions": 104,
    "followers": "11"
  },
  {
    "url": "https://github.com/vsinha",
    "language": "Racket",
    "full_name": "Viraj Sinha",
    "username": "vsinha",
    "location": "West Lafayette, Indiana",
    "join_date": "Nov 3, 2012",
    "popular_repos_stars": "3",
    "primary_languages": [
      "Python",
      "Shell",
      "C"
    ],
    "contributions": 342,
    "followers": "11"
  },
  {
    "url": "https://github.com/nancoil",
    "language": "Racket",
    "full_name": "Nan Coil",
    "username": "nancoil",
    "location": "",
    "join_date": "Jun 4, 2013",
    "popular_repos_stars": "0",
    "primary_languages": [
      "JavaScript",
      "Emacs",
      "Lisp"
    ],
    "contributions": 2,
    "followers": "10"
  },
  {
    "url": "https://github.com/RaphiePS",
    "language": "Racket",
    "full_name": "Raphie Palefsky-Smith",
    "username": "RaphiePS",
    "location": "",
    "join_date": "Sep 29, 2011",
    "popular_repos_stars": "0",
    "primary_languages": [
      "JavaScript",
      "Racket"
    ],
    "contributions": 3,
    "followers": "10"
  },
  {
    "url": "https://github.com/ianj",
    "language": "Racket",
    "full_name": "J. Ian Johnson",
    "username": "ianj",
    "location": "Boston, MA",
    "join_date": "Apr 1, 2011",
    "popular_repos_stars": "13",
    "primary_languages": [
      "Racket",
      "TeX",
      "Shell"
    ],
    "contributions": 291,
    "followers": "10"
  },
  {
    "url": "https://github.com/nelliemckesson",
    "language": "Racket",
    "full_name": "Nellie McKesson",
    "username": "nelliemckesson",
    "location": "Brooklyn, NY",
    "join_date": "May 26, 2011",
    "popular_repos_stars": "11",
    "primary_languages": [
      "CSS",
      "JavaScript",
      "Perl"
    ],
    "contributions": 670,
    "followers": "10"
  },
  {
    "url": "https://github.com/samvv",
    "language": "Racket",
    "full_name": "Sam Vervaeck",
    "username": "samvv",
    "location": "Belgium",
    "join_date": "Nov 11, 2012",
    "popular_repos_stars": "52",
    "primary_languages": [
      "Shell",
      "Racket",
      "C"
    ],
    "contributions": 64,
    "followers": "9"
  },
  {
    "url": "https://github.com/nanosec",
    "language": "Racket",
    "full_name": "",
    "username": "nanosec",
    "location": "",
    "join_date": "Jul 25, 2013",
    "popular_repos_stars": "0",
    "primary_languages": [
      "Julia",
      "Matlab",
      "FORTRAN"
    ],
    "contributions": 310,
    "followers": "9"
  },
  {
    "url": "https://github.com/robpe",
    "language": "Racket",
    "full_name": "",
    "username": "robpe",
    "location": "",
    "join_date": "Sep 28, 2012",
    "popular_repos_stars": "1",
    "primary_languages": [
      "Ruby",
      "Racket"
    ],
    "contributions": 13,
    "followers": "8"
  },
  {
    "url": "https://github.com/zanezhang",
    "language": "Racket",
    "full_name": "",
    "username": "zanezhang",
    "location": "",
    "join_date": "Jul 22, 2012",
    "popular_repos_stars": "6",
    "primary_languages": [
      "Racket",
      "Erlang",
      "Ruby"
    ],
    "contributions": 3,
    "followers": "8"
  },
  {
    "url": "https://github.com/lehitoskin",
    "language": "Racket",
    "full_name": "Lehi Toskin",
    "username": "lehitoskin",
    "location": "",
    "join_date": "Oct 7, 2012",
    "popular_repos_stars": "36",
    "primary_languages": [
      "Racket",
      "JavaScript",
      "C"
    ],
    "contributions": 352,
    "followers": "8"
  },
  {
    "url": "https://github.com/rapacity",
    "language": "Racket",
    "full_name": "",
    "username": "rapacity",
    "location": "",
    "join_date": "Jan 24, 2011",
    "popular_repos_stars": "8",
    "primary_languages": [
      "Racket",
      "C"
    ],
    "contributions": 0,
    "followers": "8"
  },
  {
    "url": "https://github.com/grettke",
    "language": "Racket",
    "full_name": "Grant Rettke",
    "username": "grettke",
    "location": "",
    "join_date": "Oct 9, 2012",
    "popular_repos_stars": "36",
    "primary_languages": [
      "Shell",
      "Emacs",
      "Lisp",
      "JavaScript"
    ],
    "contributions": 112,
    "followers": "8"
  },
  {
    "url": "https://github.com/athyuttamre",
    "language": "Racket",
    "full_name": "Athyuttam Reddy",
    "username": "athyuttamre",
    "location": "Providence, RI",
    "join_date": "Feb 29, 2012",
    "popular_repos_stars": "2",
    "primary_languages": [
      "JavaScript",
      "CSS",
      "Ruby"
    ],
    "contributions": 339,
    "followers": "8"
  },
  {
    "url": "https://github.com/Zoetermeer",
    "language": "Racket",
    "full_name": "James Swaine",
    "username": "Zoetermeer",
    "location": "",
    "join_date": "Oct 28, 2009",
    "popular_repos_stars": "2",
    "primary_languages": [
      "Racket",
      "Shell",
      "Python"
    ],
    "contributions": 63,
    "followers": "8"
  },
  {
    "url": "https://github.com/clklein",
    "language": "Racket",
    "full_name": "",
    "username": "clklein",
    "location": "",
    "join_date": "Jan 16, 2011",
    "popular_repos_stars": "11",
    "primary_languages": [
      "Racket",
      "Python",
      "Assembly"
    ],
    "contributions": 0,
    "followers": "7"
  },
  {
    "url": "https://github.com/rawdiggie",
    "language": "Racket",
    "full_name": "Genc Rashiti",
    "username": "rawdiggie",
    "location": "Berlin, Germany",
    "join_date": "Oct 9, 2010",
    "popular_repos_stars": "0",
    "primary_languages": [
      "Ruby",
      "CSS"
    ],
    "contributions": 5,
    "followers": "7"
  },
  {
    "url": "https://github.com/haselhorst",
    "language": "Racket",
    "full_name": "",
    "username": "haselhorst",
    "location": "",
    "join_date": "Mar 1, 2012",
    "popular_repos_stars": "1",
    "primary_languages": [
      "Racket"
    ],
    "contributions": 0,
    "followers": "6"
  },
  {
    "url": "https://github.com/sekude",
    "language": "Racket",
    "full_name": "Sebastian Kudelka",
    "username": "sekude",
    "location": "Jülich Germany",
    "join_date": "Jan 9, 2013",
    "popular_repos_stars": "0",
    "primary_languages": [
      "Shell",
      "Python",
      "CSS"
    ],
    "contributions": 17,
    "followers": "6"
  },
  {
    "url": "https://github.com/Aaronik",
    "language": "Racket",
    "full_name": "Aaron Sullivan",
    "username": "Aaronik",
    "location": "",
    "join_date": "Jan 12, 2012",
    "popular_repos_stars": "10",
    "primary_languages": [
      "JavaScript",
      "CSS",
      "Ruby"
    ],
    "contributions": 404,
    "followers": "6"
  },
  {
    "url": "https://github.com/salmans",
    "language": "Racket",
    "full_name": "Salman Saghafi",
    "username": "salmans",
    "location": "",
    "join_date": "Feb 1, 2012",
    "popular_repos_stars": "2",
    "primary_languages": [
      "Alloy",
      "Java"
    ],
    "contributions": 2,
    "followers": "6"
  },
  {
    "url": "https://github.com/Metaxal",
    "language": "Racket",
    "full_name": "Laurent Orseau",
    "username": "Metaxal",
    "location": "",
    "join_date": "Apr 18, 2012",
    "popular_repos_stars": "34",
    "primary_languages": [
      "Racket",
      "Java",
      "Shell"
    ],
    "contributions": 316,
    "followers": "6"
  },
  {
    "url": "https://github.com/soharu",
    "language": "Racket",
    "full_name": "",
    "username": "soharu",
    "location": "Seoul, Korea",
    "join_date": "Jan 13, 2012",
    "popular_repos_stars": "3",
    "primary_languages": [
      "CSS",
      "Racket"
    ],
    "contributions": 112,
    "followers": "6"
  },
  {
    "url": "https://github.com/waniji",
    "language": "Racket",
    "full_name": "Makoto Sasaki",
    "username": "waniji",
    "location": "Tokyo",
    "join_date": "Mar 11, 2012",
    "popular_repos_stars": "0",
    "primary_languages": [
      "Perl",
      "Shell",
      "CSS"
    ],
    "contributions": 127,
    "followers": "6"
  },
  {
    "url": "https://github.com/samdphillips",
    "language": "Racket",
    "full_name": "Sam Phillips",
    "username": "samdphillips",
    "location": "Oakland, California",
    "join_date": "Oct 9, 2010",
    "popular_repos_stars": "9",
    "primary_languages": [
      "Racket",
      "Python",
      "Ruby"
    ],
    "contributions": 66,
    "followers": "6"
  },
  {
    "url": "https://github.com/bdj",
    "language": "Racket",
    "full_name": "Blake Johnson",
    "username": "bdj",
    "location": "Provo, UT",
    "join_date": "Apr 19, 2010",
    "popular_repos_stars": "9",
    "primary_languages": [
      "Racket",
      "C",
      "Scheme"
    ],
    "contributions": 12,
    "followers": "6"
  }
]