[
  {
    "url": "https://github.com/Guite",
    "language": "Xtend",
    "full_name": "Axel Guckelsberger",
    "username": "Guite",
    "location": "Germany",
    "join_date": "May 15, 2010",
    "popular_repos_stars": "40",
    "primary_languages": [
      "JavaScript",
      "CSS",
      "Shell"
    ],
    "contributions": 1,
    "followers": "37"
  },
  {
    "url": "https://github.com/Gonzalo-F",
    "language": "Xtend",
    "full_name": "",
    "username": "Gonzalo-F",
    "location": "",
    "join_date": "Mar 28, 2014",
    "popular_repos_stars": "0",
    "primary_languages": [
      "Xtend",
      "Java"
    ],
    "contributions": 108,
    "followers": "6"
  }
]