[
  {
    "url": "https://github.com/tolmasky",
    "language": "Objective-J"
  },
  {
    "url": "https://github.com/Me1000",
    "language": "Objective-J"
  },
  {
    "url": "https://github.com/primalmotion",
    "language": "Objective-J"
  },
  {
    "url": "https://github.com/eliaskg",
    "language": "Objective-J"
  },
  {
    "url": "https://github.com/saikat",
    "language": "Objective-J"
  },
  {
    "url": "https://github.com/aljungberg",
    "language": "Objective-J"
  },
  {
    "url": "https://github.com/austinsarner",
    "language": "Objective-J"
  },
  {
    "url": "https://github.com/mmcfadyen91",
    "language": "Objective-J"
  },
  {
    "url": "https://github.com/paulbaumgart",
    "language": "Objective-J"
  },
  {
    "url": "https://github.com/cacaodev",
    "language": "Objective-J"
  },
  {
    "url": "https://github.com/stevegeek",
    "language": "Objective-J"
  },
  {
    "url": "https://github.com/codehate",
    "language": "Objective-J"
  },
  {
    "url": "https://github.com/korenyushkin",
    "language": "Objective-J"
  },
  {
    "url": "https://github.com/mdufort",
    "language": "Objective-J"
  },
  {
    "url": "https://github.com/ConnorD",
    "language": "Objective-J"
  },
  {
    "url": "https://github.com/davidcann",
    "language": "Objective-J"
  },
  {
    "url": "https://github.com/hholtmann",
    "language": "Objective-J"
  },
  {
    "url": "https://github.com/Dogild",
    "language": "Objective-J"
  },
  {
    "url": "https://github.com/davisml",
    "language": "Objective-J"
  },
  {
    "url": "https://github.com/jukart",
    "language": "Objective-J"
  },
  {
    "url": "https://github.com/mikecsh",
    "language": "Objective-J"
  },
  {
    "url": "https://github.com/nadley",
    "language": "Objective-J"
  },
  {
    "url": "https://github.com/meirtsvi",
    "language": "Objective-J"
  },
  {
    "url": "https://github.com/Zouuup",
    "language": "Objective-J"
  },
  {
    "url": "https://github.com/spakanati",
    "language": "Objective-J"
  },
  {
    "url": "https://github.com/angerman",
    "language": "Objective-J"
  }
]