[
  {
    "url": "https://github.com/glassesfactory",
    "language": "ActionScript"
  },
  {
    "url": "https://github.com/gskinner",
    "language": "ActionScript"
  },
  {
    "url": "https://github.com/codegangsta",
    "language": "ActionScript"
  },
  {
    "url": "https://github.com/AdamAtomic",
    "language": "ActionScript"
  },
  {
    "url": "https://github.com/robertpenner",
    "language": "ActionScript"
  },
  {
    "url": "https://github.com/johnlindquist",
    "language": "ActionScript"
  },
  {
    "url": "https://github.com/photonstorm",
    "language": "ActionScript"
  },
  {
    "url": "https://github.com/joelhooks",
    "language": "ActionScript"
  },
  {
    "url": "https://github.com/PrimaryFeather",
    "language": "ActionScript"
  },
  {
    "url": "https://github.com/destroytoday",
    "language": "ActionScript"
  },
  {
    "url": "https://github.com/darscan",
    "language": "ActionScript"
  },
  {
    "url": "https://github.com/claus",
    "language": "ActionScript"
  },
  {
    "url": "https://github.com/amitp",
    "language": "ActionScript"
  },
  {
    "url": "https://github.com/inspirit",
    "language": "ActionScript"
  },
  {
    "url": "https://github.com/joshtynjala",
    "language": "ActionScript"
  },
  {
    "url": "https://github.com/MoritzStefaner",
    "language": "ActionScript"
  },
  {
    "url": "https://github.com/richardlord",
    "language": "ActionScript"
  },
  {
    "url": "https://github.com/theflashbum",
    "language": "ActionScript"
  },
  {
    "url": "https://github.com/hype",
    "language": "ActionScript"
  },
  {
    "url": "https://github.com/Actionscript3Commons",
    "language": "ActionScript"
  },
  {
    "url": "https://github.com/Stray",
    "language": "ActionScript"
  },
  {
    "url": "https://github.com/grapefrukt",
    "language": "ActionScript"
  },
  {
    "url": "https://github.com/spicefactory",
    "language": "ActionScript"
  },
  {
    "url": "https://github.com/cantrell",
    "language": "ActionScript"
  },
  {
    "url": "https://github.com/DaftMonk",
    "language": "ActionScript"
  },
  {
    "url": "https://github.com/renaun",
    "language": "ActionScript"
  },
  {
    "url": "https://github.com/alamboley",
    "language": "ActionScript"
  },
  {
    "url": "https://github.com/darronschall",
    "language": "ActionScript"
  },
  {
    "url": "https://github.com/tpryan",
    "language": "ActionScript"
  },
  {
    "url": "https://github.com/zrong",
    "language": "ActionScript"
  },
  {
    "url": "https://github.com/drewbourne",
    "language": "ActionScript"
  },
  {
    "url": "https://github.com/bengarney",
    "language": "ActionScript"
  },
  {
    "url": "https://github.com/Draknek",
    "language": "ActionScript"
  },
  {
    "url": "https://github.com/mraad",
    "language": "ActionScript"
  },
  {
    "url": "https://github.com/kyoji2",
    "language": "ActionScript"
  },
  {
    "url": "https://github.com/arpit",
    "language": "ActionScript"
  },
  {
    "url": "https://github.com/thibaultimbert",
    "language": "ActionScript"
  },
  {
    "url": "https://github.com/army8735",
    "language": "ActionScript"
  },
  {
    "url": "https://github.com/alecmce",
    "language": "ActionScript"
  },
  {
    "url": "https://github.com/newtriks",
    "language": "ActionScript"
  },
  {
    "url": "https://github.com/wouterverweirder",
    "language": "ActionScript"
  },
  {
    "url": "https://github.com/FrancisVarga",
    "language": "ActionScript"
  },
  {
    "url": "https://github.com/benstucki",
    "language": "ActionScript"
  },
  {
    "url": "https://github.com/srohde",
    "language": "ActionScript"
  },
  {
    "url": "https://github.com/GustavoCostaW",
    "language": "ActionScript"
  },
  {
    "url": "https://github.com/nodename",
    "language": "ActionScript"
  },
  {
    "url": "https://github.com/lo-th",
    "language": "ActionScript"
  },
  {
    "url": "https://github.com/zmLiu",
    "language": "ActionScript"
  },
  {
    "url": "https://github.com/fljot",
    "language": "ActionScript"
  },
  {
    "url": "https://github.com/probertson",
    "language": "ActionScript"
  },
  {
    "url": "https://github.com/lannymcnie",
    "language": "ActionScript"
  },
  {
    "url": "https://github.com/MattesGroeger",
    "language": "ActionScript"
  },
  {
    "url": "https://github.com/k5342",
    "language": "ActionScript"
  },
  {
    "url": "https://github.com/TerryCavanagh",
    "language": "ActionScript"
  },
  {
    "url": "https://github.com/trxcllnt",
    "language": "ActionScript"
  },
  {
    "url": "https://github.com/liaocheng",
    "language": "ActionScript"
  },
  {
    "url": "https://github.com/cassiozen",
    "language": "ActionScript"
  },
  {
    "url": "https://github.com/eidiot",
    "language": "ActionScript"
  },
  {
    "url": "https://github.com/katopz",
    "language": "ActionScript"
  },
  {
    "url": "https://github.com/Papervision3D",
    "language": "ActionScript"
  },
  {
    "url": "https://github.com/logotype",
    "language": "ActionScript"
  },
  {
    "url": "https://github.com/disjukr",
    "language": "ActionScript"
  },
  {
    "url": "https://github.com/sammyt",
    "language": "ActionScript"
  },
  {
    "url": "https://github.com/tomkrcha",
    "language": "ActionScript"
  },
  {
    "url": "https://github.com/johnyanarella",
    "language": "ActionScript"
  },
  {
    "url": "https://github.com/Matan",
    "language": "ActionScript"
  },
  {
    "url": "https://github.com/schlangster",
    "language": "ActionScript"
  },
  {
    "url": "https://github.com/cellfusion",
    "language": "ActionScript"
  },
  {
    "url": "https://github.com/skyboy",
    "language": "ActionScript"
  },
  {
    "url": "https://github.com/pshtif",
    "language": "ActionScript"
  },
  {
    "url": "https://github.com/eladelrom",
    "language": "ActionScript"
  },
  {
    "url": "https://github.com/nulldesign",
    "language": "ActionScript"
  },
  {
    "url": "https://github.com/Dovyski",
    "language": "ActionScript"
  },
  {
    "url": "https://github.com/dabing1022",
    "language": "ActionScript"
  },
  {
    "url": "https://github.com/s9tpepper",
    "language": "ActionScript"
  },
  {
    "url": "https://github.com/XavierCHN",
    "language": "ActionScript"
  },
  {
    "url": "https://github.com/jesses",
    "language": "ActionScript"
  },
  {
    "url": "https://github.com/kingfo",
    "language": "ActionScript"
  },
  {
    "url": "https://github.com/flashhawk",
    "language": "ActionScript"
  },
  {
    "url": "https://github.com/labriola",
    "language": "ActionScript"
  },
  {
    "url": "https://github.com/ryancampbell",
    "language": "ActionScript"
  },
  {
    "url": "https://github.com/og2t",
    "language": "ActionScript"
  },
  {
    "url": "https://github.com/ton1517",
    "language": "ActionScript"
  },
  {
    "url": "https://github.com/lucasmotta",
    "language": "ActionScript"
  },
  {
    "url": "https://github.com/mikecann",
    "language": "ActionScript"
  },
  {
    "url": "https://github.com/lukesh",
    "language": "ActionScript"
  },
  {
    "url": "https://github.com/jrmoretti",
    "language": "ActionScript"
  },
  {
    "url": "https://github.com/emedinaa",
    "language": "ActionScript"
  },
  {
    "url": "https://github.com/rscheitlin",
    "language": "ActionScript"
  },
  {
    "url": "https://github.com/stickupkid",
    "language": "ActionScript"
  },
  {
    "url": "https://github.com/richardolsson",
    "language": "ActionScript"
  },
  {
    "url": "https://github.com/itoz",
    "language": "ActionScript"
  },
  {
    "url": "https://github.com/jankeesvw",
    "language": "ActionScript"
  },
  {
    "url": "https://github.com/zachwlewis",
    "language": "ActionScript"
  },
  {
    "url": "https://github.com/theturtle32",
    "language": "ActionScript"
  },
  {
    "url": "https://github.com/SeanHogan",
    "language": "ActionScript"
  },
  {
    "url": "https://github.com/mikedotalmond",
    "language": "ActionScript"
  },
  {
    "url": "https://github.com/larsiusprime",
    "language": "ActionScript"
  },
  {
    "url": "https://github.com/creynders",
    "language": "ActionScript"
  },
  {
    "url": "https://github.com/xtyler",
    "language": "ActionScript"
  }
]