[
  {
    "url": "https://github.com/bos",
    "language": "Haskell"
  },
  {
    "url": "https://github.com/ekmett",
    "language": "Haskell"
  },
  {
    "url": "https://github.com/tonymorris",
    "language": "Haskell"
  },
  {
    "url": "https://github.com/chrisdone",
    "language": "Haskell"
  },
  {
    "url": "https://github.com/jgm",
    "language": "Haskell"
  },
  {
    "url": "https://github.com/mariusaeriksen",
    "language": "Haskell"
  },
  {
    "url": "https://github.com/simonmar",
    "language": "Haskell"
  },
  {
    "url": "https://github.com/snoyberg",
    "language": "Haskell"
  },
  {
    "url": "https://github.com/evancz",
    "language": "Haskell"
  },
  {
    "url": "https://github.com/copumpkin",
    "language": "Haskell"
  },
  {
    "url": "https://github.com/jaspervdj",
    "language": "Haskell"
  },
  {
    "url": "https://github.com/batterseapower",
    "language": "Haskell"
  },
  {
    "url": "https://github.com/tibbe",
    "language": "Haskell"
  },
  {
    "url": "https://github.com/kazu-yamamoto",
    "language": "Haskell"
  },
  {
    "url": "https://github.com/chriseidhof",
    "language": "Haskell"
  },
  {
    "url": "https://github.com/ezyang",
    "language": "Haskell"
  },
  {
    "url": "https://github.com/colah",
    "language": "Haskell"
  },
  {
    "url": "https://github.com/jonsterling",
    "language": "Haskell"
  },
  {
    "url": "https://github.com/tanakh",
    "language": "Haskell"
  },
  {
    "url": "https://github.com/joeyh",
    "language": "Haskell"
  },
  {
    "url": "https://github.com/ocharles",
    "language": "Haskell"
  },
  {
    "url": "https://github.com/Gabriel439",
    "language": "Haskell"
  },
  {
    "url": "https://github.com/pbrisbin",
    "language": "Haskell"
  },
  {
    "url": "https://github.com/bjin",
    "language": "Haskell"
  },
  {
    "url": "https://github.com/mraleph",
    "language": "Haskell"
  },
  {
    "url": "https://github.com/simonpj",
    "language": "Haskell"
  },
  {
    "url": "https://github.com/dysinger",
    "language": "Haskell"
  },
  {
    "url": "https://github.com/edwinb",
    "language": "Haskell"
  },
  {
    "url": "https://github.com/MaskRay",
    "language": "Haskell"
  },
  {
    "url": "https://github.com/thoughtpolice",
    "language": "Haskell"
  },
  {
    "url": "https://github.com/cartazio",
    "language": "Haskell"
  },
  {
    "url": "https://github.com/jekor",
    "language": "Haskell"
  },
  {
    "url": "https://github.com/feuerbach",
    "language": "Haskell"
  },
  {
    "url": "https://github.com/brow",
    "language": "Haskell"
  },
  {
    "url": "https://github.com/jgoerzen",
    "language": "Haskell"
  },
  {
    "url": "https://github.com/byorgey",
    "language": "Haskell"
  },
  {
    "url": "https://github.com/vincenthz",
    "language": "Haskell"
  },
  {
    "url": "https://github.com/jkff",
    "language": "Haskell"
  },
  {
    "url": "https://github.com/mchakravarty",
    "language": "Haskell"
  },
  {
    "url": "https://github.com/yihuang",
    "language": "Haskell"
  },
  {
    "url": "https://github.com/dpiponi",
    "language": "Haskell"
  },
  {
    "url": "https://github.com/TikhonJelvis",
    "language": "Haskell"
  },
  {
    "url": "https://github.com/gregorycollins",
    "language": "Haskell"
  },
  {
    "url": "https://github.com/conal",
    "language": "Haskell"
  },
  {
    "url": "https://github.com/singpolyma",
    "language": "Haskell"
  },
  {
    "url": "https://github.com/kfish",
    "language": "Haskell"
  },
  {
    "url": "https://github.com/fumieval",
    "language": "Haskell"
  },
  {
    "url": "https://github.com/mzero",
    "language": "Haskell"
  },
  {
    "url": "https://github.com/kmcallister",
    "language": "Haskell"
  },
  {
    "url": "https://github.com/mightybyte",
    "language": "Haskell"
  },
  {
    "url": "https://github.com/yogsototh",
    "language": "Haskell"
  },
  {
    "url": "https://github.com/sebastiaanvisser",
    "language": "Haskell"
  },
  {
    "url": "https://github.com/maoe",
    "language": "Haskell"
  },
  {
    "url": "https://github.com/mwotton",
    "language": "Haskell"
  },
  {
    "url": "https://github.com/divarvel",
    "language": "Haskell"
  },
  {
    "url": "https://github.com/solidsnack",
    "language": "Haskell"
  },
  {
    "url": "https://github.com/pi8027",
    "language": "Haskell"
  },
  {
    "url": "https://github.com/BartMassey",
    "language": "Haskell"
  },
  {
    "url": "https://github.com/rrnewton",
    "language": "Haskell"
  },
  {
    "url": "https://github.com/kosmikus",
    "language": "Haskell"
  },
  {
    "url": "https://github.com/pigworker",
    "language": "Haskell"
  },
  {
    "url": "https://github.com/basvandijk",
    "language": "Haskell"
  },
  {
    "url": "https://github.com/HeinrichApfelmus",
    "language": "Haskell"
  },
  {
    "url": "https://github.com/nfjinjing",
    "language": "Haskell"
  },
  {
    "url": "https://github.com/dterei",
    "language": "Haskell"
  },
  {
    "url": "https://github.com/egisatoshi",
    "language": "Haskell"
  },
  {
    "url": "https://github.com/sol",
    "language": "Haskell"
  },
  {
    "url": "https://github.com/nominolo",
    "language": "Haskell"
  },
  {
    "url": "https://github.com/aculich",
    "language": "Haskell"
  },
  {
    "url": "https://github.com/dmalikov",
    "language": "Haskell"
  },
  {
    "url": "https://github.com/roman",
    "language": "Haskell"
  },
  {
    "url": "https://github.com/clockfort",
    "language": "Haskell"
  },
  {
    "url": "https://github.com/sjoerdvisscher",
    "language": "Haskell"
  },
  {
    "url": "https://github.com/ozataman",
    "language": "Haskell"
  },
  {
    "url": "https://github.com/eagletmt",
    "language": "Haskell"
  },
  {
    "url": "https://github.com/valderman",
    "language": "Haskell"
  },
  {
    "url": "https://github.com/gwern",
    "language": "Haskell"
  },
  {
    "url": "https://github.com/BartoszMilewski",
    "language": "Haskell"
  },
  {
    "url": "https://github.com/yav",
    "language": "Haskell"
  },
  {
    "url": "https://github.com/jochu",
    "language": "Haskell"
  },
  {
    "url": "https://github.com/ndmitchell",
    "language": "Haskell"
  },
  {
    "url": "https://github.com/rianhunter",
    "language": "Haskell"
  },
  {
    "url": "https://github.com/dcoutts",
    "language": "Haskell"
  },
  {
    "url": "https://github.com/melpon",
    "language": "Haskell"
  },
  {
    "url": "https://github.com/norm2782",
    "language": "Haskell"
  },
  {
    "url": "https://github.com/luqui",
    "language": "Haskell"
  },
  {
    "url": "https://github.com/chris-taylor",
    "language": "Haskell"
  },
  {
    "url": "https://github.com/nh2",
    "language": "Haskell"
  },
  {
    "url": "https://github.com/bjpop",
    "language": "Haskell"
  },
  {
    "url": "https://github.com/alpmestan",
    "language": "Haskell"
  },
  {
    "url": "https://github.com/mikeizbicki",
    "language": "Haskell"
  },
  {
    "url": "https://github.com/osa1",
    "language": "Haskell"
  },
  {
    "url": "https://github.com/darinmorrison",
    "language": "Haskell"
  },
  {
    "url": "https://github.com/tomahawkins",
    "language": "Haskell"
  },
  {
    "url": "https://github.com/luite",
    "language": "Haskell"
  },
  {
    "url": "https://github.com/jfischoff",
    "language": "Haskell"
  },
  {
    "url": "https://github.com/kim",
    "language": "Haskell"
  },
  {
    "url": "https://github.com/freizl",
    "language": "Haskell"
  },
  {
    "url": "https://github.com/nlogax",
    "language": "Haskell"
  },
  {
    "url": "https://github.com/myuon",
    "language": "Haskell"
  }
]