[
  {
    "url": "https://github.com/AFNetworking/AFNetworking",
    "size": 19470,
    "language": "Objective-C"
  },
  {
    "url": "https://github.com/facebookarchive/three20",
    "size": 33231,
    "language": "Objective-C"
  },
  {
    "url": "https://github.com/BradLarson/GPUImage",
    "size": 45344,
    "language": "Objective-C"
  },
  {
    "url": "https://github.com/RestKit/RestKit",
    "size": 76030,
    "language": "Objective-C"
  },
  {
    "url": "https://github.com/rs/SDWebImage",
    "size": 10727,
    "language": "Objective-C"
  },
  {
    "url": "https://github.com/jdg/MBProgressHUD",
    "size": 2381,
    "language": "Objective-C"
  },
  {
    "url": "https://github.com/ReactiveCocoa/ReactiveCocoa",
    "size": 26308,
    "language": "Objective-C"
  },
  {
    "url": "https://github.com/magicalpanda/MagicalRecord",
    "size": 17023,
    "language": "Objective-C"
  },
  {
    "url": "https://github.com/pokeb/asi-http-request",
    "size": 6748,
    "language": "Objective-C"
  },
  {
    "url": "https://github.com/ccgus/fmdb",
    "size": 3258,
    "language": "Objective-C"
  },
  {
    "url": "https://github.com/Grouper/FlatUIKit",
    "size": 2694,
    "language": "Objective-C"
  },
  {
    "url": "https://github.com/facebook/facebook-ios-sdk",
    "size": 21246,
    "language": "Objective-C"
  },
  {
    "url": "https://github.com/johnezang/JSONKit",
    "size": 707,
    "language": "Objective-C"
  },
  {
    "url": "https://github.com/jigish/slate",
    "size": 48772,
    "language": "Objective-C"
  },
  {
    "url": "https://github.com/jverkoey/nimbus",
    "size": 52144,
    "language": "Objective-C"
  },
  {
    "url": "https://github.com/Mantle/Mantle",
    "size": 5772,
    "language": "Objective-C"
  },
  {
    "url": "https://github.com/path/FastImageCache",
    "size": 34857,
    "language": "Objective-C"
  },
  {
    "url": "https://github.com/Inferis/ViewDeck",
    "size": 2318,
    "language": "Objective-C"
  },
  {
    "url": "https://github.com/TransitApp/SVProgressHUD",
    "size": 2408,
    "language": "Objective-C"
  },
  {
    "url": "https://github.com/facebook/Shimmer",
    "size": 3250,
    "language": "Objective-C"
  }
]