[
  {
    "url": "https://github.com/arclanguage/anarki",
    "size": 4746,
    "language": "Arc"
  },
  {
    "url": "https://github.com/wting/hackernews",
    "size": 170,
    "language": "Arc"
  },
  {
    "url": "https://github.com/bixo/bixo",
    "size": 409201,
    "language": "Arc"
  },
  {
    "url": "https://github.com/conanite/rainbow",
    "size": 1253,
    "language": "Arc"
  },
  {
    "url": "https://github.com/Treeki/Reggie",
    "size": 12327,
    "language": "Arc"
  },
  {
    "url": "https://github.com/ChrisVeigl/BrainBay",
    "size": 56879,
    "language": "Arc"
  },
  {
    "url": "https://github.com/sacado/arc2c",
    "size": 184,
    "language": "Arc"
  },
  {
    "url": "https://github.com/awwx/ar",
    "size": 1451,
    "language": "Arc"
  },
  {
    "url": "https://github.com/arclanguage/rainbow-js",
    "size": 1049,
    "language": "Arc"
  },
  {
    "url": "https://github.com/evanrmurphy/SweetScript",
    "size": 311,
    "language": "Arc"
  },
  {
    "url": "https://github.com/akkartik/arc",
    "size": 601,
    "language": "Arc"
  },
  {
    "url": "https://github.com/hasenj/sehm",
    "size": 120,
    "language": "Arc"
  },
  {
    "url": "https://github.com/Treeki/NewerSMBW",
    "size": 59083,
    "language": "Arc"
  },
  {
    "url": "https://github.com/epi/xedisk",
    "size": 680,
    "language": "Arc"
  },
  {
    "url": "https://github.com/hchbaw/swank-arc",
    "size": 76,
    "language": "Arc"
  },
  {
    "url": "https://github.com/ukwa/webarchive-test-suite",
    "size": 2484,
    "language": "Arc"
  },
  {
    "url": "https://github.com/mgiken/arc-mg",
    "size": 361,
    "language": "Arc"
  },
  {
    "url": "https://github.com/esden/elco",
    "size": 140,
    "language": "Arc"
  },
  {
    "url": "https://github.com/lsauer/Data-Hub",
    "size": 32720,
    "language": "Arc"
  },
  {
    "url": "https://github.com/shader/metagame",
    "size": 203,
    "language": "Arc"
  }
]